cloudnap/__init__.py
cloudnap/base.py
cloudnap/config.py
cloudnap/ecs.py
cloudnap-0.1.0.dist-info/LICENSE
cloudnap-0.1.0.dist-info/METADATA
cloudnap-0.1.0.dist-info/WHEEL
cloudnap-0.1.0.dist-info/RECORD
