Metadata-Version: 2.3
Name: cloudnap
Version: 0.1.0
Summary: A Python package to automate AWS resource scaling for cost optimization.
License: MIT
Author: Dilnawaz Warisi
Author-email: dilnawaz07@gmail.com
Requires-Python: >=3.10
Classifier: License :: OSI Approved :: MIT License
Classifier: Programming Language :: Python :: 3
Classifier: Programming Language :: Python :: 3.10
Classifier: Programming Language :: Python :: 3.11
Classifier: Programming Language :: Python :: 3.12
Classifier: Programming Language :: Python :: 3.13
Requires-Dist: boto3 (>=1.38)
Requires-Dist: pyyaml (>6.0)
